vspleeter/__init__.py
vspleeter/__main__.py
vspleeter/resource.qrc
vspleeter/vspleeter.png
vspleeter/vspleeter_mainWindow.ui
vspleeter/vspleeter_qrc.py
vspleeter-1.0.4.dist-info/METADATA
vspleeter-1.0.4.dist-info/WHEEL
vspleeter-1.0.4.dist-info/entry_points.txt
vspleeter-1.0.4.dist-info/top_level.txt
vspleeter-1.0.4.dist-info/RECORD
