Metadata-Version: 2.1
Name: vspleeter
Version: 1.0.4
Summary: GUI wrapper of spleeter separate command.
Home-page: https://github.com/djieff/vspleeter
Author: Jean-Francois Bouchard
Author-email: bouchard.jfrancois@gmail.com
License: MIT license
Keywords: vspleeter
Platform: UNKNOWN
Classifier: Development Status :: 2 - Pre-Alpha
Classifier: Intended Audience :: Developers
Classifier: License :: OSI Approved :: MIT License
Classifier: Natural Language :: English
Classifier: Programming Language :: Python :: 3.7
Requires-Python: >=3.7
Requires-Dist: PySide2
